BlockOL/__init__.py
BlockOL-1.3.2.dist-info/LICENSE
BlockOL-1.3.2.dist-info/METADATA
BlockOL-1.3.2.dist-info/WHEEL
BlockOL-1.3.2.dist-info/top_level.txt
BlockOL-1.3.2.dist-info/RECORD
