Metadata-Version: 2.1
Name: BlockOL
Version: 1.3.2
Summary: The library which will be used by most of my scripts
Home-page: https://github.com/BlockOG/BlockOL
Author: BlockOG
Author-email: blockofgamingreal@gmail.com
Project-URL: Bug Tracker, https://github.com/BlockOG/BlockOL/issues
Classifier: Programming Language :: Python :: 3
Classifier: License :: OSI Approved :: MIT License
Classifier: Operating System :: OS Independent
Requires-Python: >=3.6
License-File: LICENSE
